handyscikit/__init__.py
handyscikit/common/__init__.py
handyscikit/common/__test_script.py
handyscikit/common/print_related.py
handyscikit/data/__init__.py
handyscikit/data/__test_script.py
handyscikit/data/data_filter.py
handyscikit/data/data_transfer.py
handyscikit/field/__init__.py
handyscikit/field/__test_script.py
handyscikit/field/physical_field.py
handyscikit/field/physical_fields.py
handyscikit/mesh/__init__.py
handyscikit/mesh/__test_script.py
handyscikit/mesh/case.py
handyscikit/mesh/core.py
handyscikit/mesh/general_mesh.py
handyscikit-1.0.1.dist-info/LICENSE
handyscikit-1.0.1.dist-info/METADATA
handyscikit-1.0.1.dist-info/WHEEL
handyscikit-1.0.1.dist-info/top_level.txt
handyscikit-1.0.1.dist-info/RECORD
