Metadata-Version: 2.1
Name: handyscikit
Version: 1.0.1
Summary: A useful simulation kit with mesh and physical fields.
Home-page: https://github.com/minho-hong/handyscikit.git
Author: Hong Peng
License: GPL
Platform: UNKNOWN
Requires-Python: >=3.7.0
License-File: LICENSE
Requires-Dist: gmsh
Requires-Dist: numpy
